Workbook

Sheet Reporte
A2: Sistema de gestión empresarial • Guatapo
A4: ="REPORTE "&Config!B2 -> REPORTE MENSUAL | J4: JULIO 2026 | 8/07/2026
A7: Ventas del periodo | D7: Ítems vendidos | G7: Beneficio neto | J7: Comisión tarjeta | L7: Comisión cooperativas | N7: Envíos
A8: =SUM(Ventas!H:H) -> 24150 | D8: =SUM(Ventas!G:G) -> 6 | G8: =SUM(Ventas!I:I) -> 5650 | J8: =SUM(Ventas!J:J) -> 0 | L8: =SUM(Ventas!K:K) -> 1070 | N8: =SUM(Ventas!L:L) -> 280
A12: RESUMEN GENERAL
A13: Concepto | B13: Cantidad | C13: Total | D13: Notas | F13: INDICADORES FINANCIEROS
A14: Ventas de contado | B14: =COUNTIF(Ventas!E:E,"normal") -> 1 | C14: =SUMIF(Ventas!E:E,"normal",Ventas!H:H) -> 2450 | D14: POS / Ventas normales | F14: Indicador | M14: Valor
A15: Ventas cooperativas | B15: =COUNTIF(Ventas!E:E,"cooperative") -> 2 | C15: =SUMIF(Ventas!E:E,"cooperative",Ventas!H:H) -> 21700 | D15: Crédito cooperativa | F15: Ventas totales | M15: =SUM(Ventas!H:H) -> 24150
A16: Cobros recibidos | B16: =COUNTA(Cooperativas!A2:A200) -> 3 | C16: =SUM(Cooperativas!E:E) -> 383000 | D16: Pagos registrados | F16: Costo de mercancía | M16: =SUM(Ventas!M:M) -> 17150
A17: Compras | B17: =COUNTA(Compras!A2:A200) -> 2 | C17: =SUM(Compras!F:F) -> 69000 | D17: Entradas de inventario | F17: Compras del periodo | M17: =SUM(Compras!F:F) -> 69000
A18: Productos activos | B18: =COUNTIF(Productos!H:H,"Activo") -> 3 | C18: =SUM(Productos!G:G) -> 306300 | D18: Inventario activo | F18: Comisiones + envíos | M18: =SUM(Ventas!J:L) -> 1350
A19: Stock bajo | B19: =COUNTIF(Productos!I:I,"Stock bajo") -> 1 | D19: Stock <= mínimo | F19: Beneficio neto | M19: =M15-M16-M18 -> 5650
A20: Agotados | B20: =COUNTIF(Productos!I:I,"Agotado") -> 1 | D20: Stock <= 0 | F20: Margen bruto | M20: =IFERROR(M19/M15,0) -> 0.23395445
A21: Cuentas por cobrar | C21: =SUM(Cooperativas!D:D) -> 202000 | D21: Facturas pendientes | F21: Ticket promedio | M21: =IFERROR(M15/COUNTA(Ventas!A2:A200),0) -> 8050
A24: PRODUCTOS MÁS VENDIDOS | H24: ALERTAS DE INVENTARIO
A25: Producto | B25: Cantidad | C25: Total | H25: Producto | I25: Categoría | J25: Stock | K25: Estado
A26: iPhone 15 Pro Max | B26: 28 | C26: 1500000 | H26: USB WiFi | I26: Redes | J26: 2 | K26: Stock bajo
A27: Samsung S24 Ultra | B27: 24 | C27: 1320000 | H27: HDMI VGA | I27: Adaptadores | J27: 1 | K27: Stock bajo
A28: AirPods Pro | B28: 21 | C28: 210000 | H28: Cable VGA | I28: Cables | J28: 0 | K28: Agotado
A29: Cargador 25W | B29: 20 | C29: 104000 | H29: Mouse Logitech | I29: Accesorios | J29: 0 | K29: Agotado
A30: Adaptador USB-C | B30: 18 | C30: 36000 | H30: Cargador Samsung | I30: Cargadores | J30: 2 | K30: Stock bajo
A34: Día | B34: Ventas
A35: 1 | B35: 2450
A36: 2 | B36: 18500
A37: 3 | B37: 3200
A38: 4 | B38: 0

Sheet Ventas
A1: Fecha | B1: Factura | C1: Cliente | D1: Cooperativa | E1: Canal | F1: Estado | G1: Ítems | H1: Total | I1: Beneficio Neto | J1: Comisión Tarjeta | K1: Comisión Cooperativa | L1: Envíos | M1: Costo Mercancía
A2: 46029 | B2: FAC-000001 | C2: Carlos Pérez | E2: normal | F2: paid | G2: 2 | H2: 2450 | I2: 650 | J2: 0 | K2: 0 | L2: 0 | M2: 1800
A3: 46088 | B3: FAC-000002 | C3: María Rodríguez | D3: COOPSEMA | E3: cooperative | F3: pending | G3: 1 | H3: 18500 | I3: 4200 | J3: 0 | K3: 920 | L3: 280 | M3: 13100
A4: 46088 | B4: FAC-000003 | C4: Luis Martínez | D4: COOPSET | E4: cooperative | F4: paid | G4: 3 | H4: 3200 | I4: 800 | J4: 0 | K4: 150 | L4: 0 | M4: 2250

Sheet Productos
A1: Producto | B1: Categoría | C1: Marca | D1: Modelo | E1: Stock | F1: Costo | G1: Valor Inventario | H1: Estado | I1: Alerta
A2: iPhone 15 Pro Max | B2: Celulares | C2: Apple | D2: 15 Pro Max | E2: 5 | F2: 61000 | G2: =E2*F2 -> 305000 | H2: Activo | I2: OK
A3: USB WiFi | B3: Redes | C3: TP-Link | D3: AC600 | E3: 2 | F3: 650 | G3: =E3*F3 -> 1300 | H3: Activo | I3: Stock bajo
A4: Cable VGA | B4: Cables | C4: Genérico | D4: VGA | E4: 0 | F4: 150 | G4: =E4*F4 -> 0 | H4: Activo | I4: Agotado

Sheet Cooperativas
A1: Cooperativa | B1: Facturas | C1: Total Facturado | D1: Pendiente | E1: Cobrado | F1: Comisión
A2: COOPSEMA | B2: 12 | C2: 240000 | D2: 85000 | E2: 155000 | F2: 9200
A3: COOPSET | B3: 6 | C3: 130000 | D3: 45000 | E3: 85000 | F3: 5300
A4: COOPECOGRAL | B4: 10 | C4: 215000 | D4: 72000 | E4: 143000 | F4: 7800

Sheet Compras
A1: Fecha | B1: Proveedor | C1: Referencia | D1: Productos | E1: Unidades | F1: Precio Por unidad | G1: Total Compra
A2: 46029 | B2: Proveedor Demo | C2: F001-000123 | D2: Dell latitude 7420 | E2: 10 | F2: 18200 | G2: =ComprasTable[[#This Row],[Precio Por unidad]]*ComprasTable[[#This Row],[Unidades]] -> 182000
A3: 46029 | B3: Distribuidor X | C3: F001-000124 | D3: 16 PRO MAX 256GB | E3: 6 | F3: 50800 | G3: =ComprasTable[[#This Row],[Precio Por unidad]]*ComprasTable[[#This Row],[Unidades]] -> 304800

Sheet Config
A1: Campo | B1: Valor
A2: Tipo de reporte | B2: MENSUAL
A3: Fecha inicio | B3: 46204
A4: Fecha fin | B4: 46234
A5: Periodo mostrado | B5: Julio 2026
A6: Generado | B6: 46211.448
A7: Negocio | B7: Guatapo
A8: Sistema | B8: CastelNova OS
A9: RNC | B9: 131974661
A10: Teléfono | B10: 809-636-1020
A11: Email | B11: info@guatapo.com
A12: Plantilla | B12: Reporte Ejecutivo
A13: Moneda | B13: RD$
A14: Notas | B14: Los datos son generados automáticamente desde Guatapo OS
